{
  "Version": "2012-10-17",
  "Statement": [
    {
      "Sid": "EC2Full",
      "Effect": "Allow",
      "Action": [
        "ec2:Describe*",
        "ec2:Get*",
        "ec2:RunInstances",
        "ec2:TerminateInstances",
        "ec2:StopInstances",
        "ec2:StartInstances",
        "ec2:RebootInstances",
        "ec2:ModifyInstanceAttribute",
        "ec2:MonitorInstances",
        "ec2:UnmonitorInstances",
        "ec2:CreateVolume",
        "ec2:DeleteVolume",
        "ec2:AttachVolume",
        "ec2:DetachVolume",
        "ec2:ModifyVolume*",
        "ec2:CreateTags",
        "ec2:DeleteTags",
        "ec2:CreateLaunchTemplate*",
        "ec2:DeleteLaunchTemplate*",
        "ec2:ModifyLaunchTemplate"
      ],
      "Resource": "*"
    },
    {
      "Sid": "EC2Networking",
      "Effect": "Allow",
      "Action": [
        "ec2:CreateVpc",
        "ec2:DeleteVpc",
        "ec2:ModifyVpcAttribute",
        "ec2:*Vpc*",
        "ec2:CreateSubnet",
        "ec2:DeleteSubnet",
        "ec2:ModifySubnetAttribute",
        "ec2:CreateInternetGateway",
        "ec2:DeleteInternetGateway",
        "ec2:AttachInternetGateway",
        "ec2:DetachInternetGateway",
        "ec2:CreateRouteTable",
        "ec2:DeleteRouteTable",
        "ec2:CreateRoute",
        "ec2:DeleteRoute",
        "ec2:ReplaceRoute",
        "ec2:AssociateRouteTable",
        "ec2:DisassociateRouteTable",
        "ec2:ReplaceRouteTableAssociation",
        "ec2:CreateSecurityGroup",
        "ec2:DeleteSecurityGroup",
        "ec2:AuthorizeSecurityGroup*",
        "ec2:RevokeSecurityGroup*",
        "ec2:ModifySecurityGroupRules",
        "ec2:UpdateSecurityGroupRuleDescriptions*",
        "ec2:CreateNetworkInterface",
        "ec2:DeleteNetworkInterface",
        "ec2:ModifyNetworkInterfaceAttribute"
      ],
      "Resource": "*"
    },
    {
      "Sid": "EC2KeyPairs",
      "Effect": "Allow",
      "Action": [
        "ec2:*KeyPair*"
      ],
      "Resource": "*"
    },
    {
      "Sid": "SSMFull",
      "Effect": "Allow",
      "Action": [
        "ssm:SendCommand",
        "ssm:GetCommandInvocation",
        "ssm:ListCommand*",
        "ssm:CancelCommand",
        "ssm:DescribeInstance*",
        "ssm:GetDocument",
        "ssm:DescribeDocument*",
        "ssm:ListDocument*",
        "ssm:StartSession",
        "ssm:TerminateSession",
        "ssm:ResumeSession",
        "ssm:DescribeSessions",
        "ssm:GetConnectionStatus"
      ],
      "Resource": "*"
    },
    {
      "Sid": "IAMRoles",
      "Effect": "Allow",
      "Action": [
        "iam:CreateRole",
        "iam:DeleteRole",
        "iam:GetRole",
        "iam:ListRoles",
        "iam:UpdateRole",
        "iam:TagRole",
        "iam:UntagRole",
        "iam:ListRoleTags",
        "iam:*RolePolicy",
        "iam:ListRolePolicies",
        "iam:ListAttachedRolePolicies",
        "iam:CreateInstanceProfile",
        "iam:DeleteInstanceProfile",
        "iam:GetInstanceProfile",
        "iam:ListInstanceProfile*",
        "iam:AddRoleToInstanceProfile",
        "iam:RemoveRoleFromInstanceProfile",
        "iam:TagInstanceProfile",
        "iam:UntagInstanceProfile",
        "iam:PassRole"
      ],
      "Resource": [
        "arn:aws:iam::*:role/ll-win-client-*",
        "arn:aws:iam::*:role/tc-*",
        "arn:aws:iam::*:instance-profile/ll-win-client-*",
        "arn:aws:iam::*:instance-profile/tc-*"
      ]
    },
    {
      "Sid": "SecretsManager",
      "Effect": "Allow",
      "Action": [
        "secretsmanager:*"
      ],
      "Resource": [
        "arn:aws:secretsmanager:*:*:secret:ll-win-client/*",
        "arn:aws:secretsmanager:*:*:secret:ll-win-client-*",
        "arn:aws:secretsmanager:*:*:secret:tc/*",
        "arn:aws:secretsmanager:*:*:secret:tc-*"
      ]
    },
    {
      "Sid": "CloudWatchLogs",
      "Effect": "Allow",
      "Action": [
        "logs:*"
      ],
      "Resource": [
        "arn:aws:logs:*:*:log-group:/aws/ec2/ll-win-client-*",
        "arn:aws:logs:*:*:log-group:/aws/ec2/ll-win-client-*:*",
        "arn:aws:logs:*:*:log-group:/aws/ec2/tc-*",
        "arn:aws:logs:*:*:log-group:/aws/ec2/tc-*:*"
      ]
    },
    {
      "Sid": "CloudWatchLogsDescribe",
      "Effect": "Allow",
      "Action": [
        "logs:Describe*"
      ],
      "Resource": "*"
    },
    {
      "Sid": "CostExplorer",
      "Effect": "Allow",
      "Action": [
        "ce:Get*"
      ],
      "Resource": "*"
    }
  ]
}
